logcatcolor/__init__.py
logcatcolor/column.py
logcatcolor/config.py
logcatcolor/format.py
logcatcolor/layout.py
logcatcolor/main.py
logcatcolor/profile.py
logcatcolor/reader.py
logcat_color3-0.10.0.dist-info/LICENSE
logcat_color3-0.10.0.dist-info/METADATA
logcat_color3-0.10.0.dist-info/WHEEL
logcat_color3-0.10.0.dist-info/entry_points.txt
logcat_color3-0.10.0.dist-info/top_level.txt
logcat_color3-0.10.0.dist-info/RECORD
