Metadata-Version: 2.1
Name: logcat-color3
Version: 0.10.0
Summary: A colorful alternative to "adb logcat"
Home-page: https://github.com/yan12125/logcat-color
Author: Marshall Culpepper
Author-email: marshall.law@gmail.com
Maintainer: Chih-Hsuan Yen
Maintainer-email: yan12125@gmail.com
License: Apache 2.0
License-File: LICENSE
Requires-Dist: colorama
Requires-Dist: pyasyncore ; python_version >= "3.12"
Requires-Dist: pyasynchat ; python_version >= "3.12"
